Workbook

Sheet CV Summary
A1: Hana Aliyah Mufidah
A2: Full Stack Developer
A4: Location | B4: Yogyakarta, ID
A5: Phone | B5: +62 858-1099-4772
A6: Email | B6: aliyanamu@gmail.com
A7: CV Source | B7: Hana_Aliyah_Mufidah.pdf (Nov 14, 2025)
A9: Summary
A10: Highly motivated individual with experience in building scalable applications for work management and B2B payment systems (Web 2.5). Proficient in both front-end and back-end development using React.js, Next.js, Node.js, and AWS. Experienced in integrating traditional and blockchain-based payment systems, with a focus on crypto-to-fiat on-/off-ramp solutions.
A12: Professional Experience
A13: Role | B13: Company | C13: Period | D13: Highlights
A14: Mid-level Software Developer | B14: Nespay | C14: Apr 2025 - Present | D14: Core architecture, AWS auth, CI/CD (GitHub Actions on EC2); led Backoffice Dashboard (React/Next.js) + backend; wallet transactions, invoice mgmt, Xellar/Privy wallets; RPC + KYC (Sumsub, Kredibel); peer code reviews.
A15: Full Stack Software Engineer | B15: ION | C15: Feb 2020 - Dec 2024 | D15: Maintained legacy + work management web apps; HRIS integration app; enhanced praise/endorsement w/ filters & leaderboards; improved time-off + work timeline w/ bulk approvals & public holidays; stabilized input components & validation.
A16: Full Stack Web Developer | B16: Ultra Voucher | C16: Nov 2018 - Jan 2020 | D16: Built dashboard apps for business needs; highlight: web app for generating digital voucher codes, tracking status, and generating reports — replaced manual Excel-based voucher tracking.
A18: Education
A19: B.S. Geophysical Engineering — Bandung Institute of Technology (Sep 2015)
A20: Javascript Fullstack Immersive Program — Hacktiv8 (Nov 2018)
A22: Key Skills
A23: • Full stack JavaScript (Nest.js, Next.js, React.js, Node.js)
A24: • Databases (MySQL, PostgreSQL, MongoDB, Neo4j, Elasticsearch, Redis)
A25: • AWS cloud services
A26: • DevOps (Docker, Ansible, Vagrant)
A27: • End-to-end testing (Nightwatch, Selenium, Mocha)
A28: • Blockchain / Web3 payment integrations (crypto-to-fiat on-/off-ramp)
A30: Accomplishments & Certifications
A31: • 3rd place — DeFi Track, EDU Chain Hackathon (May 2025)
... A33: • Languages: English (Professional), Korean (Conversational)

Sheet Dashboard
A1: Job Hunting — Pipeline Overview
A3: Status | B3: Count | D3: Companies on radar | E3: Count
A4: Wishlist | B4: =COUNTA(Wishlist!C2:C1000) | D4: Tracked (portals.yml) | E4: =COUNTA(Companies!B3:B98)
A5: Evaluated | B5: =COUNTIF(Applications!H:H,"Evaluated") | D5: Marked Interested | E5: =COUNTIF(Companies!F3:F98,"Interested")
A6: Applied | B6: =COUNTIF(Applications!H:H,"Applied") | D6: Marked Applied | E6: =COUNTIF(Companies!F3:F98,"Applied")
A7: Responded | B7: =COUNTIF(Applications!H:H,"Responded") | D7: Marked Watching | E7: =COUNTIF(Companies!F3:F98,"Watching")
A8: Interview | B8: =COUNTIF(Applications!H:H,"Interview")
A9: Offer | B9: =COUNTIF(Applications!H:H,"Offer")
A10: Rejected | B10: =COUNTIF(Applications!H:H,"Rejected")
A11: Discarded | B11: =COUNTIF(Applications!H:H,"Discarded")
A12: SKIP | B12: =COUNTIF(Applications!H:H,"SKIP")
A13: TOTAL applications | B13: =COUNTA(Applications!C2:C1000)

Sheet Wishlist
A1: # | B1: Date Added | C1: Company | D1: Role | E1: Job URL | F1: Source | G1: Work Eligibility | H1: Why Interested | I1: Fit Score (1-5) | J1: Deadline | K1: Decision | L1: Notes
A2: =ROW()-1 | B2: 2026-05-06 | C2: Espresso Systems | D2: Software Engineer, Infrastructure | E2: https://jobs.lever.co/Espresso/bf359a02-5579-4d8b-a254-23c989f67af5 | F2: User-added (Lever) | H2: WEB3 • USER PICK • Rust-preferred (C++/Haskell ok) | I2: 5 | K2: 1. Apply | L2: Loc: Remote (global) | Rust preferred (not required)
A3: =ROW()-1 | B3: 2026-05-06 | C3: Tether | D3: Backend Engineer - Wallets (100% Remote) | E3: https://careers.tether.io/o/backend-engineer-wallets-100-remote-29 | F3: User-added (Tether careers) | H3: WEB3 • USDT issuer • SAME-TZ ⭐ | I3: 5 | K3: 1. Apply | L3: Loc: VN | verify: GLOBAL_OK (JSON-LD)
A4: =ROW()-1 | B4: 2026-05-06 | C4: Tether | D4: Senior Frontend Developer (100% Remote Worldwide) | E4: https://careers.tether.io/o/senior-frontend-developer-kyc-worldwide | F4: User-added (Tether careers) | H4: WEB3 • USDT issuer • SAME-TZ ⭐ | I4: 5 | K4: 1. Apply | L4: Loc: AE,CZ,EG,ES,HR,IN,IT,MY,NL,VN | verify: GLOBAL_OK (JSON-LD)
A5: =ROW()-1 | B5: 2026-05-06 | C5: Tether | D5: Senior Fullstack Developer (100% remote Worldwide) | E5: https://careers.tether.io/o/senior-fullstack-developer-100-remote-worldwide | F5: User-added (Tether careers) | H5: WEB3 • USDT issuer | I5: 5 | K5: 1. Apply | L5: Loc: AE,CH,ES,GR,IN,IT,NG,NL | verify: GLOBAL_OK (JSON-LD)
A6: =ROW()-1 | B6: 2026-05-06 | C6: Tether | D6: Senior Backend Developer | E6: https://careers.tether.io/o/senior-backend-developer-norway | F6: User-added (Tether careers) | H6: WEB3 • USDT issuer | I6: 5 | K6: 3. Saved | L6: Loc: NO | verify: GLOBAL_OK (JSON-LD)
A7: =ROW()-1 | B7: 2026-05-06 | C7: Tether | D7: Senior Backend Developer | E7: https://careers.tether.io/o/senior-backend-developer-sweden | F7: User-added (Tether careers) | H7: WEB3 • USDT issuer | I7: 5 | K7: 3. Saved | L7: Loc: SE | verify: GLOBAL_OK (JSON-LD)
A8: =ROW()-1 | B8: 2026-05-06 | C8: Tether | D8: Senior Frontend Developer (100% remote) | E8: https://careers.tether.io/o/senior-frontend-developer-100-remote-hungria | F8: User-added (Tether careers) | H8: WEB3 • USDT issuer | I8: 5 | K8: 3. Saved | L8: Loc: IT | verify: GLOBAL_OK (JSON-LD)
A9: =ROW()-1 | B9: 2026-05-06 | C9: Supabase | D9: Software Engineer - Support Tooling (APAC/AMER) | E9: https://jobs.ashbyhq.com/supabase/2ed5e80d-438b-47a5-9efe-12d168b8de81 | F9: career-ops scan | H9: GLOBAL-verified • Tier A | I9: 5 | K9: 4. Pending | L9: Loc: | verify: GLOBAL_OK
A10: =ROW()-1 | B10: 2026-05-06 | C10: n8n | D10: Sr AI Engineer | E10: https://jobs.ashbyhq.com/n8n/d195a389-6af5-4b95-82e5-2258953c7297 | F10: career-ops scan | H10: REMOTE-unverified • Tier A | I10: 4 | K10: 4. Pending | L10: Loc: Remote - Europe | TS/Vue/NodeJS | verify: unclear
A11: =ROW()-1 | B11: 2026-05-06 | C11: n8n | D11: Sr Cloud Engineer | E11: https://jobs.ashbyhq.com/n8n/640d55b3-3603-42f4-a05b-90962768fd16 | F11: career-ops scan | H11: REMOTE-unverified • Tier A | I11: 4 | K11: 4. Pending | L11: Loc: NodeJS + TS/JS | Europe remote | verify: unclear
A12: =ROW()-1 | B12: 2026-05-06 | C12: Aleph Alpha | D12: Senior AI Software Engineer - Model Evaluation (f/m/d) | E12: https://jobs.ashbyhq.com/AlephAlpha/1963147c-dc27-416e-b432-065295733bef | F12: career-ops scan | H12: Tier A | I12: 3 | K12: 4. Pending | L12: Loc: | verify: unclear
A13: =ROW()-1 | B13: 2026-05-06 | C13: Boomi | D13: Senior Software Engineer | E13: https://boomi.com/boomi-jobs/?gh_jid=5776784004 | F13: career-ops scan | H13: Tier A | I13: 3 | K13: 4. Pending | L13: Loc: | verify: unclear
... A123: =ROW()-1 | B123: 2026-05-06 | C123: Zapier | D123: Software Engineer — Release Engineering | E123: https://jobs.ashbyhq.com/zapier/6948a0e6-a580-4e9d-b109-20652d9a1507 | F123: career-ops scan | H123: Tier A | I123: 3 | K123: 1. Apply | L123: Loc: | verify: unclear
A124: =ROW()-1 | B124: 2026-05-07 | C124: Glean | D124: Software Engineer, Backend | E124: https://job-boards.greenhouse.io/gleanwork/jobs/4581643005 | F124: career-ops scan | G124: Visa sponsorship needed | H124: Loc: San Francisco Bay Area | K124: 4. Pending
A125: =ROW()-1 | B125: 2026-05-07 | C125: Intercom | D125: Senior Full Stack Engineer - Team Web | E125: https://job-boards.greenhouse.io/intercom/jobs/7276257 | F125: career-ops scan | G125: Visa sponsorship needed | H125: Loc: London, England | K125: 4. Pending
A126: =ROW()-1 | B126: 2026-05-07 | C126: Contentful | D126: Fullstack Software Engineer (f/m/d) | E126: https://job-boards.greenhouse.io/contentful/jobs/7553930 | F126: career-ops scan | G126: Visa sponsorship needed | H126: Loc: London, England | K126: 4. Pending
A127: =ROW()-1 | B127: 2026-05-07 | C127: Contentful | D127: Senior Backend Engineer - AI Platform (f/m/d) | E127: https://job-boards.greenhouse.io/contentful/jobs/7776562 | F127: career-ops scan | G127: Visa sponsorship needed | H127: Loc: London, England | K127: 4. Pending
A128: =ROW()-1 | B128: 2026-05-07 | C128: Contentful | D128: Senior Software Engineer - Backend & Infrastructure (f/m/d) | E128: https://job-boards.greenhouse.io/contentful/jobs/7760966 | F128: career-ops scan | G128: Visa sponsorship needed | H128: Loc: Berlin, Germany | K128: 4. Pending
A129: =ROW()-1 | B129: 2026-05-07 | C129: N26 | D129: Backend Engineer - Acquire | E129: https://n26.com/en-eu/careers/positions/7742395?gh_jid=7742395 | F129: career-ops scan | G129: Visa sponsorship needed | H129: Loc: Berlin | K129: 4. Pending
A130: =ROW()-1 | B130: 2026-05-07 | C130: N26 | D130: Backend Engineer - Engagement | E130: https://n26.com/en-eu/careers/positions/7640893?gh_jid=7640893 | F130: career-ops scan | G130: Visa sponsorship needed | H130: Loc: Berlin / Barcelona | K130: 4. Pending
A131: =ROW()-1 | B131: 2026-05-07 | C131: N26 | D131: Senior Full-Stack Security Automation Engineer | E131: https://n26.com/en-eu/careers/positions/7597686?gh_jid=7597686 | F131: career-ops scan | G131: Visa sponsorship needed | H131: Loc: Barcelona | K131: 4. Pending
A132: =ROW()-1 | B132: 2026-05-07 | C132: Legora | D132: Senior Backend Engineer | E132: https://jobs.ashbyhq.com/legora/b0dcbd44-38c5-46fc-aa9a-610fe881fc1c | F132: career-ops scan | G132: Visa sponsorship needed | H132: Loc: Malmö | K132: 4. Pending
A133: =ROW()-1 | B133: 2026-05-07 | C133: Legora | D133: Senior Software Engineer | E133: https://jobs.ashbyhq.com/legora/2ec4729a-82e2-4e7b-90d9-c9afb8e941bb | F133: career-ops scan | G133: Visa sponsorship needed | H133: Loc: Stockholm HQ | K133: 4. Pending
A134: =ROW()-1 | B134: 2026-05-07 | C134: Pigment | D134: Senior Backend Software Engineer | E134: https://jobs.lever.co/pigment/bf7cacad-0f52-4db4-88d4-ad7b22bd852e | F134: career-ops scan | G134: Visa sponsorship needed | H134: Loc: France | K134: 4. Pending
E147: https://sumup.com/careers/positions/8468000002?gh_jid=8468000002
E148: https://sumup.com/careers/positions/8448678002?gh_jid=8448678002
E149: https://sumup.com/careers/positions/8520790002?gh_jid=8520790002
E150: https://sumup.com/careers/positions/8468005002?gh_jid=8468005002
E151: https://sumup.com/careers/positions/8420811002?gh_jid=8420811002
E152: https://sumup.com/careers/positions/8520406002?gh_jid=8520406002
E153: https://sumup.com/careers/positions/8468006002?gh_jid=8468006002
E154: https://sumup.com/careers/positions/7480776002?gh_jid=7480776002
A155: =ROW()-1 | B155: 2026-05-07 | C155: Shippio | D155: Senior Full-Stack Engineer | E155: https://www.gittap.jp/jobs/1720 | F155: career-ops scan / gittap.jp | G155: Visa sponsorship needed | H155: Vue/React/JS, 7.5M+ JPY, Japan relocation | K155: 2. Recommended | L155: (via GitTap)
A156: =ROW()-1 | B156: 2026-05-07 | C156: ReNK CHANNEL | D156: Front End Engineer (Visa Support) | E156: https://www.gittap.jp/jobs/5214 | F156: career-ops scan / gittap.jp | G156: Visa sponsorship needed | H156: In-house dev, listed-company subsidiary, visa support stated | K156: 4. Pending | L156: (via GitTap)
A157: =ROW()-1 | B157: 2026-05-07 | C157: stakefish | D157: Web3 / Full-stack Software Engineer | E157: https://www.linkedin.com/jobs/view/4354681451/ | F157: user-submitted (LinkedIn) | G157: Remote — worldwide (Singapore HQ, GMT+8) | H157: React+TS+Python+web3.js, mid-senior IC, distributed culture, $140-180K | I157: 5 | K157: 2. Recommended | L157: User-flagged as ideal fit shape (2026-05-07)

Sheet Preparations
A1: # | B1: Date | C1: Company | D1: Role | E1: Job URL | F1: Tailored CV Path | G1: Tailored CV Status | H1: Q1: Why this role? | I1: Q2: Why this company? | J1: Q3: Relevant experience | K1: Q4: Why a good fit? | L1: Q5: How did you hear? | M1: Other custom Qs | N1: Video required? | O1: Video script notes | P1: Video status | Q1: AI disclaimer? | R1: Submission status | S1: Notes
A2: =ROW()-1 | B2: 2026-05-06 | C2: Tether | D2: Backend Engineer (Wallets) — 100% Remote | E2: https://careers.tether.io/o/backend-engineer-wallets-100-remote-29 | F2: career-ops/output/cv-hana-aliyah-mufidah-tether-2026-05-06.pdf | G2: Done (4.5/5 evaluated) | H2: Wallet platform is exactly where I have been working — at Nespay I built backend + admin for a B2B crypto-to-fiat product (Xellar, Privy, MySQL, MongoDB). Tether operates the same problem at the scale I want to learn next. | I2: USDT is infrastructure I have worked around since I started in Web3. The chance to work on the wallet layer (not on top of it) is rare and matches my current Nespay work directly. | J2: Lead architecture, AWS, and backend on Nespay's B2B crypto-to-fiat platform — wallet transactions, invoice management, KYC. 5 years prior at ION on a complex work-management platform. 3rd place EDU Chain Hackathon DeFi Track (May 2025). | K2: I sit at the intersection of Node.js backend craft and Web3 wallet integration — the two stacks the JD names. Both shipped in production within the last 12 months. | L2: Through my own job-search workflow. Tether ranked highest against my criteria. | M2: — | N2: YES (per Tether application) | O2: 60–90s; open with 1 specific Tether product I have used; one sentence on why wallet backend specifically; one Nespay proof point (Node.js + MySQL + Xellar); close with 1 question for the team. Bullets only — no script reading. | P2: Not recorded | Q2: YES — rewrite all drafts in own voice before pasting | R2: Not submitted | S2: Score 4.5/5 — see career-ops/reports/001-tether-2026-05-06.md
A3: =ROW()-1 | B3: 2026-05-06 | C3: Tether | D3: Senior Frontend Developer — KYC, Worldwide | E3: https://careers.tether.io/o/senior-frontend-developer-kyc-worldwide | F3: career-ops/output/cv-hana-aliyah-mufidah-tether-fe-kyc-2026-05-06.pdf | G3: Done (4.2/5 evaluated) | H3: KYC compliance is the part of crypto product I have spent the past year on — at Nespay I integrated Sumsub and Kredibel end-to-end on a React/Next admin and customer flow. Bitfinex KYC is the same problem at much larger scale. | I3: Bitfinex KYC is one of the most stress-tested compliance surfaces in crypto. The chance to ship into that environment, on a stack (React, Redux, Node, MongoDB) that maps to what I already use, is rare. | J3: 5 yrs of frontend at ION on a complex enterprise platform — debugging hidden issues, condition-based UI logic, input validation. Now leading the Backoffice Dashboard (React/Next) at Nespay including KYC integration UX with Sumsub and Kredibel. 7+ yrs JS/TS overall. | K3: I bring React + KYC integration experience already in production, plus enough backend (Node.js, MongoDB, RPC) to run the app locally and reason across the stack — which the JD asks for explicitly. | L3: Through my own job-search workflow. Tether ranked highest against my criteria. | M3: Senior title gap: I am Mid-level by title, senior by scope. Be ready to defend if asked. | N3: YES (per Tether application) | O3: 60–90s; open with one specific Bitfinex KYC pain point I have observed; one sentence on why frontend specifically (React/Redux + KYC); one Nespay proof (Sumsub + Kredibel on React/Next); one question on KYC roadmap. Bullets only. | P3: Not recorded | Q3: YES — rewrite all drafts in own voice before pasting | R3: Not submitted | S3: Score 4.2/5 — see career-ops/reports/002-tether-2026-05-06.md. Gaps: Redux + SASS not on CV; brush up Redux Toolkit before interview.
A4: =ROW()-1 | B4: 2026-05-07 | C4: Tether | D4: Senior Fullstack Developer — 100% Remote Worldwide | E4: https://careers.tether.io/o/senior-fullstack-developer-100-remote-worldwide | F4: career-ops/output/cv-hana-aliyah-mufidah-tether-fs-2026-05-07.pdf | G4: Done (4.0/5 evaluated) | H4: Rewrite in own voice — see report H | I4: Rewrite in own voice — see report H | J4: Rewrite in own voice — see report H | K4: Rewrite in own voice — see report H | L4: Rewrite in own voice — see report H | M4: Senior title gap: Mid-level by title, senior by scope. Honest framing on Kubernetes (Docker only in prod) and Holepunch (will read docs). | N4: TBD — check on submission | O4: 60-90s; open with Nespay multi-provider failover anecdote (no user impact); one sentence on backend-emphasis fullstack (vs. FE-only); one question: how the platform handles GPU job scheduling under contention. Bullets only — do not script. | P4: Not recorded | Q4: YES — rewrite all drafts in own voice before pasting | R4: Not submitted | S4: Score 4.0/5 — see career-ops/reports/003-tether-fs-2026-05-07.md. Gaps (all preferred only): Kubernetes, Holepunch p2p, AI/ML infra.

Sheet Applications
A1: # | B1: Date Applied | C1: Company | D1: Role | E1: Location / Remote | F1: Source / Portal | G1: Job URL | H1: Status | I1: Last Update | J1: CV Used | K1: Cover Letter | L1: Application Link | M1: Salary / Range | N1: Contact (name, email/LI) | O1: Next Action | P1: Follow-up Date | Q1: Notes
A2: =ROW()-1
A3: =ROW()-1
A4: =ROW()-1
A5: =ROW()-1
A6: =ROW()-1
A7: =ROW()-1
A8: =ROW()-1
A9: =ROW()-1
A10: =ROW()-1
A11: =ROW()-1
A12: =ROW()-1
A13: =ROW()-1
... A201: =ROW()-1

Sheet Companies
A1: Tracked Companies — synced from portals.yml (96 entries)
A2: # | B2: Company | C2: Careers URL | D2: Enabled | E2: Notes | F2: Status (mine)
A3: 1 | B3: Anthropic | C3: https://job-boards.greenhouse.io/anthropic | D3: Yes
A4: 2 | B4: OpenAI | C4: https://openai.com/careers | D4: Yes
A5: 3 | B5: PolyAI | C5: https://job-boards.eu.greenhouse.io/polyai | D5: Yes | E5: UK. Voice AI for enterprise contact centers.
A6: 4 | B6: Parloa | C6: https://job-boards.eu.greenhouse.io/parloa | D6: Yes | E6: Berlin EMEA. Voice AI enterprise.
A7: 5 | B7: Intercom | C7: https://job-boards.greenhouse.io/intercom | D7: Yes | E7: Dublin EMEA. Fin AI agent.
A8: 6 | B8: Hume AI | C8: https://job-boards.greenhouse.io/humeai | D8: Yes | E8: NYC. Empathic voice AI.
A9: 7 | B9: ElevenLabs | C9: https://jobs.ashbyhq.com/elevenlabs | D9: Yes | E9: Voice AI TTS leader.
A10: 8 | B10: Deepgram | C10: https://jobs.ashbyhq.com/deepgram | D10: Yes | E10: STT/TTS APIs.
A11: 9 | B11: Vapi | C11: https://jobs.ashbyhq.com/vapi | D11: Yes | E11: Voice AI infrastructure.
A12: 10 | B12: Bland AI | C12: https://jobs.ashbyhq.com/bland | D12: Yes | E12: Voice phone agents. $65M Series B.
A13: 11 | B13: Retool | C13: https://retool.com/careers | D13: Yes | E13: London. Popularized Deployed Engineer role.
A14: 12 | B14: Airtable | C14: https://job-boards.greenhouse.io/airtable | D14: Yes | E14: No-code + AI platform.
A15: 13 | B15: Vercel | C15: https://job-boards.greenhouse.io/vercel | D15: Yes | E15: AI SDK, v0.dev. Frontend AI tooling.
A16: 14 | B16: Temporal | C16: https://job-boards.greenhouse.io/temporal | D16: Yes | E16: Workflow orchestration.
... A65: 63 | B65: Trade Republic | C65: https://job-boards.greenhouse.io/traderepublicbank | D65: Yes | E65: Berlin / London / Paris. Neobroker, ~50 roles, platform & data.
A66: 64 | B66: SumUp | C66: https://job-boards.greenhouse.io/sumup | D66: No | E66: Berlin / London. Payments fintech, EU + LATAM hiring. OFFICE-FIRST — not remote. Flexible work case-by-case via interview. Excluded from scans (relocation friction + many duplicates). | F66: Excluded
A67: 65 | B67: Qonto | C67: https://jobs.lever.co/qonto | D67: Yes | E67: Paris / Berlin / Barcelona / Milan. SMB neobank, MLOps for AI Product roles.
A68: 66 | B68: Forto | C68: https://jobs.lever.co/forto | D68: Yes | E68: Berlin DE. Digital freight forwarder, product & data roles, German + English.
A69: 67 | B69: Lakera | C69: https://jobs.ashbyhq.com/lakera.ai | D69: Yes | E69: Zurich CH / SF. AI security & guardrails. Has Forward Deployed Engineer roles.
A70: 68 | B70: Scandit | C70: https://job-boards.greenhouse.io/scandit | D70: Yes | E70: Zurich CH. Computer vision / smart data capture, ML roles.
A71: 69 | B71: Cradle | C71: https://jobs.ashbyhq.com/cradlebio | D71: Yes | E71: Zurich CH / Amsterdam. AI-guided protein design, ML researcher roles.
A72: 70 | B72: Hugging Face | C72: https://apply.workable.com/huggingface/ | D72: Yes | E72: Paris / NYC / Remote. ML hub & open-source models.
A73: 71 | B73: Photoroom | C73: https://jobs.ashbyhq.com/photoroom | D73: Yes | E73: Paris FR. AI photo editor, Head of CV / Head of ML roles.
A74: 72 | B74: Pigment | C74: https://jobs.lever.co/pigment | D74: Yes | E74: Paris FR / NYC / London. AI-powered FP&A planning platform.
A75: 73 | B75: Wayve | C75: https://job-boards.greenhouse.io/wayve | D75: No | E75: London UK / Tokyo. Self-driving AV — hardware/automotive/embedded stack (C/C++, Linux BSP, Yocto, QNX, AUTOSAR, SoC bring-up). NOT relevant to user's web/backend profile. Excluded from scans. | F75: Excluded
A76: 74 | B76: Isomorphic Labs | C76: https://job-boards.greenhouse.io/isomorphiclabs | D76: Yes | E76: London / Lausanne / Cambridge MA. DeepMind spin-out for drug discovery AI.
A77: 75 | B77: PhysicsX | C77: https://job-boards.greenhouse.io/physicsx | D77: Yes | E77: London UK. Physics-informed ML for engineering, ~40 roles.
A78: 76 | B78: Stability AI | C78: https://job-boards.greenhouse.io/stabilityai | D78: Yes | E78: London / SF. Generative AI image/video research lab.
A79: 77 | B79: Synthesia | C79: https://jobs.ashbyhq.com/synthesia | D79: Yes | E79: London UK. AI video generation for enterprise, $4B valuation.
A80: 78 | B80: Faculty | C80: https://jobs.ashbyhq.com/faculty | D80: Yes | E80: London UK. Applied AI consultancy. 80+ roles, AI Safety / MLE / Delivery.
A81: 79 | B81: Causaly | C81: https://jobs.ashbyhq.com/causaly | D81: Yes | E81: London / Athens. Biomedical knowledge graph + AI.
A82: 80 | B82: Lovable | C82: https://jobs.ashbyhq.com/lovable | D82: Yes | E82: Stockholm SE. AI app builder (text-to-app), 80+ open roles.
A83: 81 | B83: Legora | C83: https://jobs.ashbyhq.com/legora | D83: Yes | E83: Stockholm SE / NYC / London. AI-native legal workspace.
A84: 82 | B84: Spotify | C84: https://jobs.lever.co/spotify | D84: Yes | E84: Stockholm SE / NYC / London. Audio platform, large ML/personalization org.
A85: 83 | B85: Vinted | C85: https://jobs.lever.co/vinted | D85: Yes | E85: Vilnius LT / Berlin. C2C marketplace unicorn, data science & ML roles.
A86: 84 | B86: Amplemarket | C86: https://job-boards.greenhouse.io/amplemarket | D86: Yes | E86: Lisbon PT / Remote. AI-native sales platform.
A87: 85 | B87: Perplexity | C87: https://jobs.ashbyhq.com/perplexity | D87: Yes | E87: AI-native search and enterprise AI platform.
... A98: 96 | B98: Maxim AI | C98: https://www.getmaxim.ai/careers | D98: Yes | E98: AI evaluation and observability platform. Bangalore-based, mostly on-site.

Sheet Status Legend
A1: Application Status — Canonical States (career-ops)
A2: Status | B2: Description | C2: Group
A3: Wishlist | B3: Saved on Wishlist sheet, not yet applied | C3: wishlist
A4: Evaluated | B4: Offer evaluated with report, pending decision | C4: evaluated
A5: Applied | B5: Application submitted | C5: applied
A6: Responded | B6: Company has responded (not yet interview) | C6: responded
A7: Interview | B7: Active interview process | C7: interview
A8: Offer | B8: Offer received | C8: offer
A9: Rejected | B9: Rejected by company | C9: rejected
A10: Discarded | B10: Discarded by candidate or offer closed | C10: discarded
A11: SKIP | B11: Doesn't fit, don't apply | C11: skip
